aprsd_repeat_plugins/__init__.py
aprsd_repeat_plugins/lat_lon.py
aprsd_repeat_plugins/nearest.py
aprsd_repeat_plugins/version.py
aprsd_repeat_plugins/conf/__init__.py
aprsd_repeat_plugins/conf/opts.py
aprsd_repeat_plugins/conf/repeat.py
aprsd_repeat_plugins-1.2.0.dist-info/LICENSE
aprsd_repeat_plugins-1.2.0.dist-info/METADATA
aprsd_repeat_plugins-1.2.0.dist-info/WHEEL
aprsd_repeat_plugins-1.2.0.dist-info/entry_points.txt
aprsd_repeat_plugins-1.2.0.dist-info/pbr.json
aprsd_repeat_plugins-1.2.0.dist-info/top_level.txt
aprsd_repeat_plugins-1.2.0.dist-info/RECORD
