Metadata-Version: 2.1
Name: aprsd-repeat-plugins
Version: 1.2.0
Summary: APRSD Plugins for the REPEAT service
Author: Walter A. Boring IV
Author-email: waboring@hemna.com
License: MIT
Classifier: Topic :: Communications :: Ham Radio
Classifier: Operating System :: POSIX :: Linux
Classifier: Programming Language :: Python
Classifier: Programming Language :: Python :: 3.7
Classifier: Programming Language :: Python :: 3.8
Classifier: Programming Language :: Python :: 3.9
License-File: LICENSE
Requires-Dist: pbr
Requires-Dist: aprsd (>=3.0.0)
Requires-Dist: requests
Requires-Dist: pyproj
Requires-Dist: oslo.config
